pyPhyEngine/__init__.py
pyPhyEngine/collider.py
pyPhyEngine/generator.py
pyPhyEngine/models.py
pyPhyEngine/renderer.py
pyPhyEngine/utils.py
pyPhyEngine/vectors.py
pyPhyEngine/video.py
pyPhyEngine-1.0.0.dist-info/COPYING
pyPhyEngine-1.0.0.dist-info/METADATA
pyPhyEngine-1.0.0.dist-info/WHEEL
pyPhyEngine-1.0.0.dist-info/top_level.txt
pyPhyEngine-1.0.0.dist-info/RECORD
